django_objectdump-0.5.2.dist-info/DESCRIPTION.rst
django_objectdump-0.5.2.dist-info/METADATA
django_objectdump-0.5.2.dist-info/RECORD
django_objectdump-0.5.2.dist-info/WHEEL
django_objectdump-0.5.2.dist-info/metadata.json
django_objectdump-0.5.2.dist-info/pbr.json
django_objectdump-0.5.2.dist-info/top_level.txt
objectdump/__init__.py
objectdump/diagram.py
objectdump/models.py
objectdump/serializer.py
objectdump/settings.py
objectdump/tests.py
objectdump/topological_sort.py
objectdump/management/__init__.py
objectdump/management/commands/__init__.py
objectdump/management/commands/object_dump.py
