Metadata-Version: 2.0
Name: django-objectdump
Version: 0.5.2
Summary: Export one or more objects and their related objects. Allows for fine-tuned control over which related objects are exported.
Home-page: https://github.com/callowayproject/django-objectdump
Author: Corey Oordt
Author-email: coreyoordt@gmail.com
License: UNKNOWN
Platform: UNKNOWN
Classifier: Framework :: Django
